pacmine/__init__.py
pacmine/__main__.py
pacmine/core/__init__.py
pacmine/core/exceptions.py
pacmine/core/loaders.py
pacmine/core/search_result.py
pacmine/local/__init__.py
pacmine/local/discovery/__init__.py
pacmine/local/discovery/jar_parser.py
pacmine/local/log.py
pacmine/local/persistence.py
pacmine/local/serialize/__init__.py
pacmine/local/serialize/repo_state.py
pacmine/local/serialize/serializer.py
pacmine/remote/__init__.py
pacmine/remote/api.py
pacmine/remote/curse_api.py
pacmine/remote/dl_result.py
pacmine/remote/gateway.py
pacmine/remote/modrinth_api.py
pacmine-1.2.3.dist-info/entry_points.txt
pacmine-1.2.3.dist-info/LICENSE
pacmine-1.2.3.dist-info/WHEEL
pacmine-1.2.3.dist-info/METADATA
pacmine-1.2.3.dist-info/RECORD
