Metadata-Version: 2.1
Name: pacmine
Version: 1.2.3
Summary: Simple package manager-esque mod manager for Minecraft
Home-page: https://gitlab.com/TheBicameralMind/pacmine
Author: aidan
Author-email: aidan.chaplin@gmail.com
Requires-Python: >=3.9,<4.0
Classifier: Programming Language :: Python :: 3
Classifier: Programming Language :: Python :: 3.9
Requires-Dist: Columnar (>=1.3.1,<2.0.0)
Requires-Dist: arrow (>=1.1.1,<2.0.0)
Requires-Dist: fire (>=0.4.0,<0.5.0)
Requires-Dist: requests (>=2.26.0,<3.0.0)
Requires-Dist: semantic-version (>=2.8.5,<3.0.0)
Requires-Dist: termcolor (>=1.1.0,<2.0.0)
Requires-Dist: tqdm (>=4.62.0,<5.0.0)
